Workbook

Sheet Inputs
A1: Input | B1: Value | C1: Note
A2: Notes principal | B2: 175000000
A3: Notes coupon rate | B3: 0.0775
A4: Make-whole discount rate (hard-coded, prior-quarter template) | B4: 0.039141918 | C4: STALE: hard-coded from a prior-quarter template; does not reference '../04_market_data_treasury_fred_fed/treasury_daily_par_yield_curve_extract.csv'. Propagates to a make-whole amount due of approximately 200,148,004.07.
A5: Day-count constant (hard-coded, shared model convention) | B5: Actual/Actual ICMA | C5: HARD-CODED: the note's own governing convention (senior_notes_indenture.pdf Sec2.01) is 30/360, not Actual/Actual ICMA.
A6: Working-capital collar adjustment basis | B6: excess-over-collar only | C6: HARD-CODED: should adjust by the full difference once the dead-band is breached.
A7: Notes par call date | B7: 47649
A8: Notes legal maturity date | B8: 48014
A9: Prior coupon date | B9: 46188
A10: Next coupon date | B10: 46371
A11: Redemption / settlement date (Closing) | B11: 46295
A12: Make-whole spread (bps) | B12: 50
A13: 3 Yr Treasury (2026-06-30 curve) | B13: 0.0415
A14: 5 Yr Treasury (2026-06-30 curve) | B14: 0.0419
A15: Remaining term to par call (years, Act/365) | B15: =(B7-B11)/365 -> 3.709589
A16: Live interpolated Treasury rate (3Yr-5Yr) | B16: =B13+(B15-3)/(5-3)*(B14-B13) -> 0.041641918
A17: Live all-in discount rate (interpolated + spread) | B17: =B16+B12/10000 -> 0.046641918
A18: Nearest-tenor Treasury rate (superseded fallback) | B18: =IF(ABS(B15-3)<=ABS(B15-5),B13,B14) -> 0.0415
A19: Nearest-tenor all-in discount rate | B19: =B18+B12/10000 -> 0.0465
A20: Stale all-in discount rate (hard-coded curve + spread) | B20: =B4+B12/10000 -> 0.044141918
A21: Change-of-control put price (% of par) | B21: 1.01
A22: Revolver commitment | B22: 60000000
A23: Revolver drawn at close | B23: 12000000
A24: Legacy assumed revolver all-in rate (stale committee assumption) | B24: 0.0825
A25: Industrial Revenue Bonds outstanding par | B25: 24500000
A26: Industrial Revenue Bonds assumed rate | B26: 0.0425
A27: Maximum Total Net Leverage covenant (Credit Agreement) | B27: 5.25
A28: Minimum Fixed Charge Coverage Ratio covenant (Credit Agreement) | B28: 1.25
A29: Internal credit policy maximum pro forma leverage | B29: 5.5
A30: LTM EBITDA (GAAP base, legacy/stale) | B30: 38500000
A31: LTM Consolidated Interest Expense | B31: 15700000

Sheet Debt Schedule
A1: Instrument | B1: Opening Balance | C1: Drawdown | D1: Repayment | E1: Interest (period) | F1: Closing Balance
A2: Revolving Credit Facility | B2: =Inputs!B23 -> 12000000 | C2: 0 | D2: 0 | E2: =B2*Inputs!B24 -> 990000 | F2: =B2+C2-D2 -> 12000000
A3: Senior Notes (Assumed Outstanding) | B3: =Inputs!B2 -> 175000000 | C3: 0 | D3: 0 | E3: =B3*Inputs!B3 -> 13562500 | F3: =B3+C3-D3 -> 175000000
A4: Industrial Revenue Bonds (Assumed at Closing) | B4: =Inputs!B25 -> 24500000 | C4: 0 | D4: 0 | E4: =B4*Inputs!B26 -> 1041250 | F4: =B4+C4-D4 -> 24500000
A5: Total | B5: =SUM(B2:B4) -> 211500000 | C5: =SUM(C2:C4) -> 0 | D5: =SUM(D2:D4) -> 0 | E5: =SUM(E2:E4) -> 15593750 | F5: =SUM(F2:F4) -> 211500000

Sheet Covenant
A1: Metric | B1: Value | C1: Threshold | D1: Pass/Fail
A2: Total Net Leverage (Total Debt / LTM EBITDA) | B2: ='Debt Schedule'!F5/Inputs!B30 -> 5.4935065 | C2: =Inputs!B27 -> 5.25 | D2: =IF(B2<=C2,"Compliant","Breach") -> Breach
A3: Fixed Charge Coverage (LTM EBITDA / Total Interest) | B3: =Inputs!B30/'Debt Schedule'!E5 -> 2.4689379 | C3: =Inputs!B28 -> 1.25 | D3: =IF(B3>=C3,"Compliant","Breach") -> Compliant
A4: Internal Credit Policy Pro Forma Leverage | B4: =B2 -> 5.4935065 | C4: =Inputs!B29 -> 5.5 | D4: =IF(B4<=C4,"Compliant","Breach") -> Compliant

Sheet Returns
A1: Metric | B1: Value
A2: Entry Enterprise Value | B2: 352000000
A3: Entry EBITDA multiple (EV/EBITDA) | B3: 8
A4: Entry Net Debt (Debt Schedule total, legacy) | B4: ='Debt Schedule'!F5 -> 211500000
A5: Implied Sponsor Equity Check (EV - Net Debt) | B5: =B2-B4 -> 140500000
A6: Legacy assumed annual EBITDA growth (hold period) | B6: 0.04
A7: Legacy assumed hold period (years) | B7: 3
A8: Assumed Exit EBITDA | B8: =Inputs!B30*(1+B6)^B7 -> 43307264
A9: Assumed Exit Multiple (flat to entry) | B9: =B3 -> 8
A10: Assumed Exit Enterprise Value | B10: =B8*B9 -> 346458112
A11: Assumed Exit Net Debt (flat, no scheduled paydown modelled) | B11: =B4 -> 211500000
A12: Assumed Exit Equity Value | B12: =B10-B11 -> 134958112
A13: Assumed MOIC (Exit Equity / Entry Equity) | B13: =B12/B5 -> 0.96055596
A14: Assumed IRR (approx, MOIC^(1/hold)-1) | B14: =B13^(1/B7)-1 -> -0.013324775
A15: Working capital peg (SPA Article II) | B15: 28400000
A16: Working capital at closing (completion accounts) | B16: 26900000
A17: Working capital collar / dead-band | B17: 750000
A18: Working capital adjustment (per Inputs basis: excess-over-collar only) | B18: =SIGN(B16-B15)*(ABS(B16-B15)-B17) -> -750000

Sheet Calc
A1: CORPORATE DEVELOPMENT - INTERNAL MODEL | B1: PRIOR-QUARTER TEMPLATE - NOT RE-TIED TO EXECUTED DOCS
A2: Notes principal | B2: 175,000,000.00
A3: Notes coupon rate | B3: 7.750%
A4: Make-whole discount rate (hard-coded, prior-quarter template) | B4: 3.914192%
A5: Make-whole spread (bps) | B5: 50
A6: Day-count constant (hard-coded, shared model convention) | B6: Actual/Actual ICMA
A7: Make-whole present value of remaining payments (this page's hard-coded discount rate) | B7: 196,192,274.90
A8: Accrued and unpaid interest (30/360) | B8: 3,955,729.17
A9: Make-whole present value (discounted through legal maturity) | B9: discounted to legal maturity (2031-06-15) instead of the par call date (2030-06-15)
A10: Make-whole amount due (accrued placement basis) | B10: accrued interest folded inside the discounted stream instead of added after the par floor
A11: Make-whole amount due (hard-coded prior-quarter discount rate) | B11: 200,148,004.07
A12: Make-whole amount due (nearest-tenor Treasury fallback) | B12: 198,550,667.30
... A18: Note | B18: Figures on this page were rolled forward from the prior quarter's model and have not been re-tied to the executed transaction documents.
A20: Period | B20: Cash Flow | C20: Live PV Factor | D20: Live PV | E20: Stale PV Factor | F20: Stale PV | G20: Nearest PV Factor | H20: Nearest PV
A21: 1 | B21: =Inputs!$B$2*Inputs!$B$3/2 -> 6781250 | C21: =POWER(1+Inputs!$B$17/2,A21) -> 1.023321 | D21: =B21/C21 -> 6626708.8 | E21: =POWER(1+Inputs!$B$20/2,A21) -> 1.022071 | F21: =B21/E21 -> 6634813.3 | G21: =POWER(1+Inputs!$B$19/2,A21) -> 1.02325 | H21: =B21/G21 -> 6627168.3
A22: 2 | B22: =Inputs!$B$2*Inputs!$B$3/2 -> 6781250 | C22: =POWER(1+Inputs!$B$17/2,A22) -> 1.0471858 | D22: =B22/C22 -> 6475689.5 | E22: =POWER(1+Inputs!$B$20/2,A22) -> 1.044629 | F22: =B22/E22 -> 6491538.8 | G22: =POWER(1+Inputs!$B$19/2,A22) -> 1.0470406 | H22: =B22/G22 -> 6476587.7
A23: 3 | B23: =Inputs!$B$2*Inputs!$B$3/2 -> 6781250 | C23: =POWER(1+Inputs!$B$17/2,A23) -> 1.0716072 | D23: =B23/C23 -> 6328111.9 | E23: =POWER(1+Inputs!$B$20/2,A23) -> 1.067685 | F23: =B23/E23 -> 6351358.3 | G23: =POWER(1+Inputs!$B$19/2,A23) -> 1.0713843 | H23: =B23/G23 -> 6329428.5
A24: 4 | B24: =Inputs!$B$2*Inputs!$B$3/2 -> 6781250 | C24: =POWER(1+Inputs!$B$17/2,A24) -> 1.0965981 | D24: =B24/C24 -> 6183897.5 | E24: =POWER(1+Inputs!$B$20/2,A24) -> 1.0912498 | F24: =B24/E24 -> 6214204.8 | G24: =POWER(1+Inputs!$B$19/2,A24) -> 1.0962939 | H24: =B24/G24 -> 6185613
A25: 5 | B25: =Inputs!$B$2*Inputs!$B$3/2 -> 6781250 | C25: =POWER(1+Inputs!$B$17/2,A25) -> 1.1221718 | D25: =B25/C25 -> 6042969.6 | E25: =POWER(1+Inputs!$B$20/2,A25) -> 1.1153348 | F25: =B25/E25 -> 6080013.1 | G25: =POWER(1+Inputs!$B$19/2,A25) -> 1.1217828 | H25: =B25/G25 -> 6045065.2
A26: 6 | B26: =Inputs!$B$2*Inputs!$B$3/2 -> 6781250 | C26: =POWER(1+Inputs!$B$17/2,A26) -> 1.1483419 | D26: =B26/C26 -> 5905253.4 | E26: =POWER(1+Inputs!$B$20/2,A26) -> 1.1399513 | F26: =B26/E26 -> 5948719.1 | G26: =POWER(1+Inputs!$B$19/2,A26) -> 1.1478642 | H26: =B26/G26 -> 5907710.9
A27: 7 | B27: =Inputs!$B$2*Inputs!$B$3/2 -> 6781250 | C27: =POWER(1+Inputs!$B$17/2,A27) -> 1.1751223 | D27: =B27/C27 -> 5770675.7 | E27: =POWER(1+Inputs!$B$20/2,A27) -> 1.1651111 | F27: =B27/E27 -> 5820260.4 | G27: =POWER(1+Inputs!$B$19/2,A27) -> 1.1745521 | H27: =B27/G27 -> 5773477.6
A28: 8 | B28: =Inputs!$B$2*Inputs!$B$3/2+Inputs!$B$2 -> 181781250 | C28: =POWER(1+Inputs!$B$17/2,A28) -> 1.2025273 | D28: =B28/C28 -> 1.51166e+08 | E28: =POWER(1+Inputs!$B$20/2,A28) -> 1.1908262 | F28: =B28/E28 -> 1.5265137e+08 | G28: =POWER(1+Inputs!$B$19/2,A28) -> 1.2018604 | H28: =B28/G28 -> 1.5124989e+08
A29: Total | B29: =SUM(B21:B28) -> 229250000 | D29: =SUM(D21:D28) -> 1.9449931e+08 | F29: =SUM(F21:F28) -> 1.9619227e+08 | H29: =SUM(H21:H28) -> 1.9459494e+08
A31: Accrued interest (30/360, live formula) | B31: =(Inputs!$B$2*Inputs!$B$3/2)*DAYS360(Inputs!$B$9,Inputs!$B$11)/180 -> 3955729.2
A32: Accrued interest (Actual/Actual ICMA, live formula) | B32: =(Inputs!$B$2*Inputs!$B$3/2)*(Inputs!$B$11-Inputs!$B$9)/(Inputs!$B$10-Inputs!$B$9) -> 3964993.2
A33: Make-whole amount due (live, correct: par floor then accrued added after) | B33: =MAX(Inputs!$B$2,D29)+B31 -> 1.9845504e+08
A34: Make-whole amount due (live, accrued folded inside the discounted stream) | B34: =MAX(Inputs!$B$2,D29+B31) -> 1.9845504e+08
A35: Change-of-control put amount due (live, correct 30/360) | B35: =Inputs!$B$21*Inputs!$B$2+B31 -> 1.8070573e+08
A36: Change-of-control put amount due (live, hard-coded Act/Act ICMA) | B36: =Inputs!$B$21*Inputs!$B$2+B32 -> 1.8071499e+08

Sheet RelativeValue
A1: Corporate note yield to worst (call-schedule search only) | B1: 8.2680143 | C1: Minimum yield across the step-down call schedule.
A2: Municipal IRB market yield (comparison basis) | B2: 0.0425
A3: Acquirer federal corporate tax rate | B3: 0.21
A4: Acquirer state corporate tax rate | B4: 0.0575
A5: Combined marginal tax rate (netted) | B5: =B3+B4*(1-B3) -> 0.255425
A6: Municipal IRB tax-equivalent yield (comparison basis) | B6: =B2/(1-B5) -> 0.057079542
A7: Note | B7: Grossed up at the firm's out-of-state marginal rate assumption.
A8: Prepared by | B8: Corporate Development - carried forward from the prior quarter's comparables model.
A9: Note | B9: Figures on this tab were rolled forward from the prior quarter's comparables model and have not been re-tied to the executed transaction documents.
